servicenow_selenium/__init__.py
servicenow_selenium/servicenow_selenium.py
servicenow_selenium-0.2.dist-info/METADATA
servicenow_selenium-0.2.dist-info/WHEEL
servicenow_selenium-0.2.dist-info/top_level.txt
servicenow_selenium-0.2.dist-info/RECORD
