Metadata-Version: 2.1
Name: servicenow-selenium
Version: 0.2
Summary: A simple selenium wrapper for ServiceNow
Home-page: https://github.com/connorwquick/servicenow-selenium
Author: Seamless Migration
Classifier: Programming Language :: Python :: 3
Classifier: License :: OSI Approved :: MIT License
Requires-Python: >=3.6
Requires-Dist: selenium
